quisual/__about__.py
quisual/__init__.py
quisual/animate.py
quisual/core.py
quisual/gates.py
quisual/pipeline_anim.py
quisual-0.0.1.dist-info/METADATA
quisual-0.0.1.dist-info/WHEEL
quisual-0.0.1.dist-info/licenses/LICENSE.txt
quisual-0.0.1.dist-info/RECORD
